mlbench/__init__.py
mlbench/ap.py
mlbench/config.py
mlbench/metrics.py
mlbench/stat.py
mlbench/utils.py
mlbench/viz.py
mlbench-0.0.3.dist-info/LICENSE
mlbench-0.0.3.dist-info/METADATA
mlbench-0.0.3.dist-info/WHEEL
mlbench-0.0.3.dist-info/top_level.txt
mlbench-0.0.3.dist-info/RECORD
