Metadata-Version: 2.1
Name: mlbench
Version: 0.0.3
Summary: ML benchmarking utils
Author-email: Amir Ziai <arziai@gmail.com>
License: MIT License
Project-URL: Homepage, https://github.com/amirziai/mlbench
Project-URL: Bug Tracker, https://github.com/amirziai/mlbench/issues
Classifier: Programming Language :: Python :: 3
Classifier: License :: OSI Approved :: MIT License
Classifier: Operating System :: OS Independent
Requires-Python: >=3.8
License-File: LICENSE
Requires-Dist: scipy
Requires-Dist: numpy
Requires-Dist: scikit-learn
Requires-Dist: pandas
Requires-Dist: matplotlib
